quizx-0.2.0.dist-info/METADATA
quizx-0.2.0.dist-info/WHEEL
quizx/__init__.py
quizx/__init__.pyi
quizx/py.typed
quizx/quizx.abi3.so
quizx-0.2.0.dist-info/RECORD
