Metadata-Version: 2.4
Name: quizx
Version: 0.2.0
Classifier: Environment :: Console
Classifier: Programming Language :: Python :: 3.9
Classifier: Programming Language :: Python :: 3.10
Classifier: Programming Language :: Python :: 3.11
Classifier: Programming Language :: Python :: 3.12
Classifier: Programming Language :: Python :: 3.13
Classifier: License :: OSI Approved :: Apache Software License
Classifier: Operating System :: MacOS :: MacOS X
Classifier: Operating System :: POSIX :: Linux
Classifier: Operating System :: Microsoft :: Windows
Classifier: Intended Audience :: Developers
Classifier: Intended Audience :: Science/Research
Classifier: Topic :: Software Development :: Compilers
Classifier: Topic :: Scientific/Engineering
Requires-Dist: pyzx>=0.9.0,<0.10.0
Summary: Quantum Circuit Optimisation and Compilation using the ZX-calculus
Home-Page: https://github.com/zxcalc/quizx
Author: Aleks Kissinger <aleks0@gmail.com>
Author-email: Aleks Kissinger <aleks0@gmail.com>
Maintainer-email: Aleks Kissinger <aleks0@gmail.com>, Agustin Borgna <agustinborgna@gmail.com>
License: Apache-2.0
Requires-Python: >=3.9
Project-URL: homepage, https://github.com/zxlang/quizx
Project-URL: repository, https://github.com/zxlang/quizx
